Metadata-Version: 1.0
Name: jiujit-probability
Version: 0.2
Summary: Gaussian and Binomial distributions
Home-page: UNKNOWN
Author: Michael Ledesma
Author-email: mxledesma@gmail.com
License: UNKNOWN
Platform: UNKNOWN
